DateTimePersian/DateTimePersian.py
DateTimePersian/__init__.py
DateTimePersian-1.3.0.dist-info/LICENSE
DateTimePersian-1.3.0.dist-info/METADATA
DateTimePersian-1.3.0.dist-info/WHEEL
DateTimePersian-1.3.0.dist-info/top_level.txt
DateTimePersian-1.3.0.dist-info/RECORD
