Metadata-Version: 2.1
Name: DateTimePersian
Version: 1.3.0
Summary: Date Time Persian
Author: Erfan Mahigir (Sarzamin Danesh Pishro)
Author-email: <info@Lssc.ir>
Keywords: python,Date,Persian,Time,Gregorian,Convert,Iranian
Classifier: Framework :: Django
Classifier: Framework :: Flask
Classifier: Framework :: FastAPI
Classifier: Framework :: Hatch
Classifier: Framework :: IDLE
Classifier: Framework :: IPython
Classifier: Framework :: Jupyter
Classifier: Framework :: Opps
Classifier: Development Status :: 5 - Production/Stable
Classifier: Intended Audience :: Developers
Classifier: Programming Language :: Python :: 3.0
Classifier: Programming Language :: Python :: 3.1
Classifier: Programming Language :: Python :: 3.2
Classifier: Programming Language :: Python :: 3.3
Classifier: Programming Language :: Python :: 3.4
Classifier: Programming Language :: Python :: 3.5
Classifier: Programming Language :: Python :: 3.6
Classifier: Programming Language :: Python :: 3.7
Classifier: Programming Language :: Python :: 3.8
Classifier: Programming Language :: Python :: 3.9
Classifier: Programming Language :: Python :: 3.10
Classifier: Programming Language :: Python :: 3.11
Classifier: Programming Language :: Python :: 3.12
Classifier: Programming Language :: Python :: 3.13
Classifier: Programming Language :: Python :: Implementation
Classifier: Operating System :: Unix
Classifier: Operating System :: MacOS :: MacOS X
Classifier: Operating System :: Microsoft :: Windows
Classifier: Operating System :: Android
Classifier: Operating System :: iOS
Classifier: License :: OSI Approved :: MIT License
License-File: LICENSE
